{"trial_id": "0024", "hyperparameters": {"space": [{"class_name": "Int", "config": {"name": "units", "default": null, "conditions": [], "min_value": 32, "max_value": 512, "step": 32, "sampling": "linear"}}, {"class_name": "Choice", "config": {"name": "learning_rate", "default": 0.01, "conditions": [], "values": [0.01, 0.001, 0.0001], "ordered": true}}], "values": {"units": 128, "learning_rate": 0.001, "tuner/epochs": 20, "tuner/initial_epoch": 7, "tuner/bracket": 1, "tuner/round": 1, "tuner/trial_id": "0022"}}, "metrics": {"metrics": {"accuracy": {"direction": "max", "observations": [{"value": [0.9931524395942688], "step": 7}]}, "loss": {"direction": "min", "observations": [{"value": [0.03888434171676636], "step": 7}]}, "val_accuracy": {"direction": "max", "observations": [{"value": [0.8652631640434265], "step": 7}]}, "val_loss": {"direction": "min", "observations": [{"value": [0.8366888761520386], "step": 7}]}}}, "score": 0.8652631640434265, "best_step": 7, "status": "COMPLETED", "message": null}